pysignalapi/__init__.py
pysignalapi/api.py
pysignalapi/engine.py
pysignalapi/messages.py
pysignalapi-0.2.7.dist-info/LICENSE
pysignalapi-0.2.7.dist-info/METADATA
pysignalapi-0.2.7.dist-info/WHEEL
pysignalapi-0.2.7.dist-info/RECORD
