Metadata-Version: 2.3
Name: pysignalapi
Version: 0.2.7
Summary: Python client for `signal-cli-rest-api`
License: MIT
Author: poterba
Maintainer: poterba
Requires-Python: >=3.9,<3.13
Classifier: License :: OSI Approved :: MIT License
Classifier: Programming Language :: Python :: 3
Classifier: Programming Language :: Python :: 3.9
Classifier: Programming Language :: Python :: 3.10
Classifier: Programming Language :: Python :: 3.11
Classifier: Programming Language :: Python :: 3.12
Requires-Dist: asyncio
Requires-Dist: dataclass-wizard
Requires-Dist: requests
Requires-Dist: websockets
Project-URL: Repository, https://github.com/poterba/pysignalapi
